{
    "rsoMass": 2000.0,
    "rsoArea": 20.0,
    "gravityDegree": 20,
    "gravityOrder": 20,
    "oceanTidesDegree": -1,
    "oceanTidesOrder": -1,
    "thirdBodySun": true,
    "thirdBodyMoon": true,
    "solidTidesSun": false,
    "solidTidesMoon": false,
    "dragModel": "MSISE",
    "dragCoefficient": {
        "value": 2.0
    },
    "rpSun": true,
    "rpCoeffReflection": {
        "value": 1.5
    },
    "propStart": "2018-01-01T00:02:54Z",
    "propEnd": "2018-01-02T00:02:54Z",
    "propStep": 300.0,
    "propInitialState": [
        35796020.7669903,
        -22267515.537321,
        -87938.3477596335,
        1625.07170292693,
        2610.77460296534,
        -2.09170251623871
    ],
    "cfgStations": {
        "Station1": {
            "latitude": 0.5578822780952235,
            "longitude": -1.8017600227679735,
            "altitude": 855.0
        }
    },
    "cfgMeasurements": {
        "azimuth": {
            "error": [
                4.8e-06
            ]
        },
        "elevation": {
            "error": [
                4.8e-06
            ]
        }
    }
}